pyEscoAPI/__init__.py
pyEscoAPI/dataclasses.py
pyEscoAPI/esco_api.py
pyEscoAPI/exception.py
pyescoapi-0.0.37.dist-info/METADATA
pyescoapi-0.0.37.dist-info/WHEEL
pyescoapi-0.0.37.dist-info/top_level.txt
pyescoapi-0.0.37.dist-info/RECORD
