Metadata-Version: 2.2
Name: pyEscoAPI
Version: 0.0.37
Summary: Python client for Esco API (Esco bolsa)
Author-email: Codetria <hola@codetria.com>
License: MIT License
Keywords: Esco,API,bolsa,client,market,provider
Classifier: Programming Language :: Python :: 3
Classifier: License :: OSI Approved :: MIT License
Classifier: Operating System :: OS Independent
Requires-Python: >=3.11
Requires-Dist: requests>=2.31.0
